{
	"$schema": "http://schema.management.azure.com/schemas/2015-01-01/deploymentTemplate.json#",
	"contentVersion": "1.0.0.0",
	"parameters": {
		"factoryName": {
			"type": "string",
			"metadata": "Data Factory name",
			"defaultValue": "adfedwfitsandbox1"
		}
	},
	"variables": {
		"factoryId": "[concat('Microsoft.DataFactory/factories/', parameters('factoryName'))]"
	},
	"resources": [
		{
			"name": "[concat(parameters('factoryName'), '/P5BI_PROFILETYPES')]",
			"type": "Microsoft.DataFactory/factories/pipelines",
			"apiVersion": "2018-06-01",
			"properties": {
				"activities": [
					{
						"name": "Execute SSIS package1",
						"type": "ExecuteSSISPackage",
						"dependsOn": [],
						"policy": {
							"timeout": "7.00:00:00",
							"retry": 0,
							"retryIntervalInSeconds": 30,
							"secureOutput": false,
							"secureInput": false
						},
						"userProperties": [],
						"typeProperties": {
							"packageLocation": {
								"packagePath": "\\\\sadwfitpoc1.file.core.windows.net\\packagedeploymentssis\\sqlserver\\ssis\\development\\BI\\SSIS\\BI_ELITA\\PR_PSA_PROTEGE_ProfileTypes.dtsx",
								"type": "File",
								"typeProperties": {
									"accessCredential": {
										"domain": "Azure",
										"userName": "sadwfitpoc1",
										"password": {
											"type": "SecureString",
											"value": "**********"
										}
									},
									"configurationPath": "\\\\sadwfitpoc1.file.core.windows.net\\packagedeploymentssis\\sqlserver\\ssis\\development\\BI\\Configuration\\BI_ELITA\\ProtegeLatamSalesApp.dtsConfig"
								}
							},
							"connectVia": {
								"referenceName": "SSISIR-customtest",
								"type": "IntegrationRuntimeReference"
							},
							"projectConnectionManagers": {},
							"packageConnectionManagers": {}
						}
					}
				],
				"policy": {
					"elapsedTimeMetric": {},
					"cancelAfter": {}
				},
				"annotations": [],
				"lastPublishTime": "2022-04-25T06:03:35Z"
			},
			"dependsOn": []
		},
		{
			"name": "[concat(parameters('factoryName'), '/P5BI_PROTEGE_FACT_SESSION')]",
			"type": "Microsoft.DataFactory/factories/pipelines",
			"apiVersion": "2018-06-01",
			"properties": {
				"activities": [
					{
						"name": "Execute SSIS package1",
						"type": "ExecuteSSISPackage",
						"dependsOn": [],
						"policy": {
							"timeout": "7.00:00:00",
							"retry": 0,
							"retryIntervalInSeconds": 30,
							"secureOutput": false,
							"secureInput": false
						},
						"userProperties": [],
						"typeProperties": {
							"packageLocation": {
								"packagePath": "\\\\sadwfitpoc1.file.core.windows.net\\packagedeploymentssis\\sqlserver\\ssis\\development\\BI\\SSIS\\BI_ELITA\\DW_Protege_Fact_Session_Load.dtsx",
								"type": "File",
								"typeProperties": {
									"accessCredential": {
										"domain": "Azure",
										"userName": "sadwfitpoc1",
										"password": {
											"type": "SecureString",
											"value": "**********"
										}
									},
									"configurationPath": "\\\\sadwfitpoc1.file.core.windows.net\\packagedeploymentssis\\sqlserver\\ssis\\development\\BI\\Configuration\\BI_ELITA\\ProtegeLatamSalesApp.dtsConfig"
								}
							},
							"connectVia": {
								"referenceName": "SSISIR-customtest",
								"type": "IntegrationRuntimeReference"
							},
							"projectConnectionManagers": {},
							"packageConnectionManagers": {}
						}
					}
				],
				"policy": {
					"elapsedTimeMetric": {},
					"cancelAfter": {}
				},
				"annotations": [],
				"lastPublishTime": "2022-04-25T06:36:30Z"
			},
			"dependsOn": []
		},
		{
			"name": "[concat(parameters('factoryName'), '/P5BI_PR_Data_Audit_Close_ETL_RUN_ID')]",
			"type": "Microsoft.DataFactory/factories/pipelines",
			"apiVersion": "2018-06-01",
			"properties": {
				"activities": [
					{
						"name": "PR_Data_Audit_Close_ETL_RUN_ID",
						"type": "ExecuteSSISPackage",
						"dependsOn": [],
						"policy": {
							"timeout": "7.00:00:00",
							"retry": 0,
							"retryIntervalInSeconds": 30,
							"secureOutput": false,
							"secureInput": false
						},
						"userProperties": [],
						"typeProperties": {
							"packageLocation": {
								"packagePath": "\\\\sadwfitpoc1.file.core.windows.net\\packagedeploymentssis\\ASBI\\SSIS\\BI_GWS_DOM\\PR_Data_Audit_Close_ETL_RUN_ID.dtsx",
								"type": "File",
								"typeProperties": {
									"accessCredential": {
										"domain": "Azure",
										"userName": "sadwfitpoc1",
										"password": {
											"type": "SecureString",
											"value": "**********"
										}
									},
									"configurationPath": "\\\\sadwfitpoc1.file.core.windows.net\\packagedeploymentssis\\ASBI\\CONFIGURATION\\BI_GWS_DOM\\DW_MS_MSHAXM_Daily_Audit.dtsConfig"
								}
							},
							"connectVia": {
								"referenceName": "SSISIR-customtest",
								"type": "IntegrationRuntimeReference"
							},
							"projectConnectionManagers": {},
							"packageConnectionManagers": {}
						}
					}
				],
				"policy": {
					"elapsedTimeMetric": {},
					"cancelAfter": {}
				},
				"annotations": [],
				"lastPublishTime": "2022-04-18T07:27:19Z"
			},
			"dependsOn": []
		},
		{
			"name": "[concat(parameters('factoryName'), '/P5BI_PR_Data_Audit_Open_ETL_RUN_ID')]",
			"type": "Microsoft.DataFactory/factories/pipelines",
			"apiVersion": "2018-06-01",
			"properties": {
				"activities": [
					{
						"name": "PR_Data_Audit_Open_ETL_RUN_ID",
						"type": "ExecuteSSISPackage",
						"dependsOn": [],
						"policy": {
							"timeout": "7.00:00:00",
							"retry": 0,
							"retryIntervalInSeconds": 30,
							"secureOutput": false,
							"secureInput": false
						},
						"userProperties": [],
						"typeProperties": {
							"packageLocation": {
								"packagePath": "\\\\sadwfitpoc1.file.core.windows.net\\packagedeploymentssis\\ASBI\\SSIS\\COMMON\\DATA_AUDIT\\PR_Data_Audit_Open_ETL_RUN_ID.dtsx",
								"type": "File",
								"typeProperties": {
									"accessCredential": {
										"domain": "Azure",
										"userName": "sadwfitpoc1",
										"password": {
											"type": "SecureString",
											"value": "**********"
										}
									},
									"configurationPath": "\\\\sadwfitpoc1.file.core.windows.net\\packagedeploymentssis\\ASBI\\CONFIGURATION\\COMMON\\DATA_AUDIT\\MS_BROADTECH_Daily_Audit.dtsConfig"
								}
							},
							"connectVia": {
								"referenceName": "SSISIR-customtest",
								"type": "IntegrationRuntimeReference"
							},
							"projectConnectionManagers": {},
							"packageConnectionManagers": {}
						}
					}
				],
				"policy": {
					"elapsedTimeMetric": {},
					"cancelAfter": {}
				},
				"annotations": [],
				"lastPublishTime": "2022-04-19T09:01:50Z"
			},
			"dependsOn": []
		},
		{
			"name": "[concat(parameters('factoryName'), '/P5BI_PTPSLSFRC_ACCOUNT')]",
			"type": "Microsoft.DataFactory/factories/pipelines",
			"apiVersion": "2018-06-01",
			"properties": {
				"activities": [
					{
						"name": "P5BI_PTPSLSFRC_ACCOUNT",
						"type": "ExecuteSSISPackage",
						"dependsOn": [],
						"policy": {
							"timeout": "7.00:00:00",
							"retry": 0,
							"retryIntervalInSeconds": 30,
							"secureOutput": false,
							"secureInput": false
						},
						"userProperties": [],
						"typeProperties": {
							"packageLocation": {
								"packagePath": "\\\\sadwfitpoc1.file.core.windows.net\\packagedeploymentssis\\sqlserver\\ssis\\development\\BI\\SSIS\\DW_GW\\DW_PTP_SALESFORCE_ACCOUNT.dtsx",
								"type": "File",
								"typeProperties": {
									"accessCredential": {
										"domain": "Azure",
										"userName": "sadwfitpoc1",
										"password": {
											"type": "SecureString",
											"value": "**********"
										}
									},
									"configurationPath": "\\\\sadwfitpoc1.file.core.windows.net\\packagedeploymentssis\\sqlserver\\ssis\\development\\BI\\Configuration\\DW_GW\\DW_PTP_SALESFORCE_FILELOAD.dtsConfig"
								}
							},
							"connectVia": {
								"referenceName": "SSISIR-customtest",
								"type": "IntegrationRuntimeReference"
							},
							"loggingLevel": "Basic",
							"projectConnectionManagers": {},
							"packageConnectionManagers": {},
							"logLocation": {
								"logPath": "\\\\sadwfitpoc1.file.core.windows.net\\packagedeploymentssis\\sqlserver\\ssis\\development\\BI\\Configuration\\DW_GW\\e938d059a28c4cb190017cdb99a63a35",
								"type": "File",
								"typeProperties": {
									"accessCredential": {
										"domain": "Azure",
										"userName": "sadwfitpoc1",
										"password": {
											"type": "SecureString",
											"value": "**********"
										}
									}
								}
							}
						}
					}
				],
				"policy": {
					"elapsedTimeMetric": {},
					"cancelAfter": {}
				},
				"annotations": [],
				"lastPublishTime": "2022-05-04T12:47:21Z"
			},
			"dependsOn": []
		},
		{
			"name": "[concat(parameters('factoryName'), '/P5BI_PTPSLSFRC_AGENTWRK')]",
			"type": "Microsoft.DataFactory/factories/pipelines",
			"apiVersion": "2018-06-01",
			"properties": {
				"activities": [
					{
						"name": "P5BI_PTPSLSFRC_AGENTWRK",
						"type": "ExecuteSSISPackage",
						"dependsOn": [],
						"policy": {
							"timeout": "7.00:00:00",
							"retry": 0,
							"retryIntervalInSeconds": 30,
							"secureOutput": false,
							"secureInput": false
						},
						"userProperties": [],
						"typeProperties": {
							"packageLocation": {
								"packagePath": "\\\\sadwfitpoc1.file.core.windows.net\\packagedeploymentssis\\sqlserver\\ssis\\development\\BI\\SSIS\\DW_GW\\DW_PTP_SALESFORCE_AGENTWORK.dtsx",
								"type": "File",
								"typeProperties": {
									"accessCredential": {
										"domain": "Azure",
										"userName": "sadwfitpoc1",
										"password": {
											"type": "SecureString",
											"value": "**********"
										}
									},
									"configurationPath": "\\\\sadwfitpoc1.file.core.windows.net\\packagedeploymentssis\\sqlserver\\ssis\\development\\BI\\Configuration\\DW_GW\\DW_PTP_SALESFORCE_FILELOAD.dtsConfig"
								}
							},
							"connectVia": {
								"referenceName": "SSISIR-customtest",
								"type": "IntegrationRuntimeReference"
							},
							"loggingLevel": "Basic",
							"projectConnectionManagers": {},
							"packageConnectionManagers": {},
							"logLocation": {
								"logPath": "\\\\sadwfitpoc1.file.core.windows.net\\packagedeploymentssis\\sqlserver\\ssis\\development\\BI\\Configuration\\DW_GW\\e938d059a28c4cb190017cdb99a63a35",
								"type": "File",
								"typeProperties": {
									"accessCredential": {
										"domain": "Azure",
										"userName": "sadwfitpoc1",
										"password": {
											"type": "SecureString",
											"value": "**********"
										}
									}
								}
							}
						}
					}
				],
				"policy": {
					"elapsedTimeMetric": {},
					"cancelAfter": {}
				},
				"annotations": [],
				"lastPublishTime": "2022-05-04T12:56:42Z"
			},
			"dependsOn": []
		},
		{
			"name": "[concat(parameters('factoryName'), '/P5BI_PTPSLSFRC_AUDIT_ETL')]",
			"type": "Microsoft.DataFactory/factories/pipelines",
			"apiVersion": "2018-06-01",
			"properties": {
				"activities": [
					{
						"name": "P5BI_PTPSLSFRC_AUDIT_ETL",
						"type": "ExecuteSSISPackage",
						"dependsOn": [],
						"policy": {
							"timeout": "7.00:00:00",
							"retry": 0,
							"retryIntervalInSeconds": 30,
							"secureOutput": false,
							"secureInput": false
						},
						"userProperties": [],
						"typeProperties": {
							"packageLocation": {
								"packagePath": "\\\\sadwfitpoc1.file.core.windows.net\\packagedeploymentssis\\sqlserver\\ssis\\development\\BI\\SSIS\\DW_GW\\DW_PTP_SALESFORCE_AUDIT.dtsx",
								"type": "File",
								"typeProperties": {
									"accessCredential": {
										"domain": "Azure",
										"userName": "sadwfitpoc1",
										"password": {
											"type": "SecureString",
											"value": "**********"
										}
									},
									"configurationPath": "\\\\sadwfitpoc1.file.core.windows.net\\packagedeploymentssis\\sqlserver\\ssis\\development\\BI\\Configuration\\DW_GW\\DW_PTP_SALESFORCE_FILELOAD.dtsConfig"
								}
							},
							"connectVia": {
								"referenceName": "SSISIR-customtest",
								"type": "IntegrationRuntimeReference"
							},
							"loggingLevel": "Basic",
							"projectConnectionManagers": {},
							"packageConnectionManagers": {},
							"logLocation": {
								"logPath": "\\\\sadwfitpoc1.file.core.windows.net\\packagedeploymentssis\\sqlserver\\ssis\\development\\BI\\Configuration\\DW_GW\\e938d059a28c4cb190017cdb99a63a35",
								"type": "File",
								"typeProperties": {
									"accessCredential": {
										"domain": "Azure",
										"userName": "sadwfitpoc1",
										"password": {
											"type": "SecureString",
											"value": "**********"
										}
									}
								}
							}
						}
					}
				],
				"policy": {
					"elapsedTimeMetric": {},
					"cancelAfter": {}
				},
				"annotations": [],
				"lastPublishTime": "2022-05-04T13:05:03Z"
			},
			"dependsOn": []
		},
		{
			"name": "[concat(parameters('factoryName'), '/P5BI_PTPSLSFRC_CASE')]",
			"type": "Microsoft.DataFactory/factories/pipelines",
			"apiVersion": "2018-06-01",
			"properties": {
				"activities": [
					{
						"name": "P5BI_PTPSLSFRC_CASE",
						"type": "ExecuteSSISPackage",
						"dependsOn": [],
						"policy": {
							"timeout": "7.00:00:00",
							"retry": 0,
							"retryIntervalInSeconds": 30,
							"secureOutput": false,
							"secureInput": false
						},
						"userProperties": [],
						"typeProperties": {
							"packageLocation": {
								"packagePath": "\\\\sadwfitpoc1.file.core.windows.net\\packagedeploymentssis\\sqlserver\\ssis\\development\\BI\\SSIS\\DW_GW\\DW_PTP_SALESFORCE_CASE.dtsx",
								"type": "File",
								"typeProperties": {
									"accessCredential": {
										"domain": "Azure",
										"userName": "sadwfitpoc1",
										"password": {
											"type": "SecureString",
											"value": "**********"
										}
									},
									"configurationPath": "\\\\sadwfitpoc1.file.core.windows.net\\packagedeploymentssis\\sqlserver\\ssis\\development\\BI\\Configuration\\DW_GW\\DW_PTP_SALESFORCE_FILELOAD.dtsConfig"
								}
							},
							"connectVia": {
								"referenceName": "SSISIR-customtest",
								"type": "IntegrationRuntimeReference"
							},
							"loggingLevel": "Basic",
							"projectConnectionManagers": {},
							"packageConnectionManagers": {},
							"logLocation": {
								"logPath": "\\\\sadwfitpoc1.file.core.windows.net\\packagedeploymentssis\\sqlserver\\ssis\\development\\BI\\Configuration\\DW_GW\\e938d059a28c4cb190017cdb99a63a35",
								"type": "File",
								"typeProperties": {
									"accessCredential": {
										"domain": "Azure",
										"userName": "sadwfitpoc1",
										"password": {
											"type": "SecureString",
											"value": "**********"
										}
									}
								}
							}
						}
					}
				],
				"policy": {
					"elapsedTimeMetric": {},
					"cancelAfter": {}
				},
				"annotations": [],
				"lastPublishTime": "2022-05-04T12:52:57Z"
			},
			"dependsOn": []
		},
		{
			"name": "[concat(parameters('factoryName'), '/P5BI_PTPSLSFRC_FLCPY')]",
			"type": "Microsoft.DataFactory/factories/pipelines",
			"apiVersion": "2018-06-01",
			"properties": {
				"activities": [
					{
						"name": "P5BI_PTPSLSFRC_FLCPY",
						"type": "ExecuteSSISPackage",
						"dependsOn": [],
						"policy": {
							"timeout": "7.00:00:00",
							"retry": 0,
							"retryIntervalInSeconds": 30,
							"secureOutput": false,
							"secureInput": false
						},
						"userProperties": [],
						"typeProperties": {
							"packageLocation": {
								"packagePath": "\\\\sadwfitpoc1.file.core.windows.net\\packagedeploymentssis\\sqlserver\\ssis\\development\\BI\\SSIS\\DW_GW\\DW_PTP_SALESFORCE_FILE_COPY.dtsx",
								"type": "File",
								"typeProperties": {
									"accessCredential": {
										"domain": "Azure",
										"userName": "sadwfitpoc1",
										"password": {
											"type": "SecureString",
											"value": "**********"
										}
									},
									"configurationPath": "\\\\sadwfitpoc1.file.core.windows.net\\packagedeploymentssis\\sqlserver\\ssis\\development\\BI\\Configuration\\DW_GW\\DW_PTP_SALESFORCE_FILELOAD.dtsConfig"
								}
							},
							"connectVia": {
								"referenceName": "SSISIR-customtest",
								"type": "IntegrationRuntimeReference"
							},
							"loggingLevel": "Basic",
							"projectConnectionManagers": {},
							"packageConnectionManagers": {},
							"logLocation": {
								"logPath": "\\\\sadwfitpoc1.file.core.windows.net\\packagedeploymentssis\\sqlserver\\ssis\\development\\BI\\Configuration\\DW_GW\\e938d059a28c4cb190017cdb99a63a35",
								"type": "File",
								"typeProperties": {
									"accessCredential": {
										"domain": "Azure",
										"userName": "sadwfitpoc1",
										"password": {
											"type": "SecureString",
											"value": "**********"
										}
									}
								}
							}
						}
					}
				],
				"policy": {
					"elapsedTimeMetric": {},
					"cancelAfter": {}
				},
				"annotations": [],
				"lastPublishTime": "2022-05-05T10:48:24Z"
			},
			"dependsOn": []
		},
		{
			"name": "[concat(parameters('factoryName'), '/P5BI_PTPSLSFRC_LIVCHTTRNSCRPT')]",
			"type": "Microsoft.DataFactory/factories/pipelines",
			"apiVersion": "2018-06-01",
			"properties": {
				"activities": [
					{
						"name": "P5BI_PTPSLSFRC_LIVCHTTRNSCRPT",
						"type": "ExecuteSSISPackage",
						"dependsOn": [],
						"policy": {
							"timeout": "7.00:00:00",
							"retry": 0,
							"retryIntervalInSeconds": 30,
							"secureOutput": false,
							"secureInput": false
						},
						"userProperties": [],
						"typeProperties": {
							"packageLocation": {
								"packagePath": "\\\\sadwfitpoc1.file.core.windows.net\\packagedeploymentssis\\sqlserver\\ssis\\development\\BI\\SSIS\\DW_GW\\DW_PTP_SALESFORCE_LIVECHATTRANSCRIPT.dtsx",
								"type": "File",
								"typeProperties": {
									"accessCredential": {
										"domain": "Azure",
										"userName": "sadwfitpoc1",
										"password": {
											"type": "SecureString",
											"value": "**********"
										}
									},
									"configurationPath": "\\\\sadwfitpoc1.file.core.windows.net\\packagedeploymentssis\\sqlserver\\ssis\\development\\BI\\Configuration\\DW_GW\\DW_PTP_SALESFORCE_FILELOAD.dtsConfig"
								}
							},
							"connectVia": {
								"referenceName": "SSISIR-customtest",
								"type": "IntegrationRuntimeReference"
							},
							"loggingLevel": "Basic",
							"projectConnectionManagers": {},
							"packageConnectionManagers": {},
							"logLocation": {
								"logPath": "\\\\sadwfitpoc1.file.core.windows.net\\packagedeploymentssis\\sqlserver\\ssis\\development\\BI\\Configuration\\DW_GW\\e938d059a28c4cb190017cdb99a63a35",
								"type": "File",
								"typeProperties": {
									"accessCredential": {
										"domain": "Azure",
										"userName": "sadwfitpoc1",
										"password": {
											"type": "SecureString",
											"value": "**********"
										}
									}
								}
							}
						}
					}
				],
				"policy": {
					"elapsedTimeMetric": {},
					"cancelAfter": {}
				},
				"annotations": [],
				"lastPublishTime": "2022-05-04T13:00:40Z"
			},
			"dependsOn": []
		},
		{
			"name": "[concat(parameters('factoryName'), '/P5BI_RECONBLUEGRASS')]",
			"type": "Microsoft.DataFactory/factories/pipelines",
			"apiVersion": "2018-06-01",
			"properties": {
				"activities": [
					{
						"name": "Execute SSIS package1",
						"type": "ExecuteSSISPackage",
						"dependsOn": [],
						"policy": {
							"timeout": "7.00:00:00",
							"retry": 0,
							"retryIntervalInSeconds": 30,
							"secureOutput": false,
							"secureInput": false
						},
						"userProperties": [],
						"typeProperties": {
							"packageLocation": {
								"packagePath": "\\\\sadwfitpoc1.file.core.windows.net\\packagedeploymentssis\\ASBI\\SSIS\\COMMON\\DATA_AUDIT\\PR_Data_Audit_Reconcile.dtsx",
								"type": "File",
								"typeProperties": {
									"accessCredential": {
										"domain": "Azure",
										"userName": "sadwfitpoc1",
										"password": {
											"type": "SecureString",
											"value": "**********"
										}
									},
									"configurationPath": "\\\\sadwfitpoc1.file.core.windows.net\\packagedeploymentssis\\ASBI\\CONFIGURATION\\COMMON\\DATA_AUDIT\\BLUEGRASS_AUDIT.dtsConfig"
								}
							},
							"connectVia": {
								"referenceName": "SSISIR-customtest",
								"type": "IntegrationRuntimeReference"
							},
							"projectConnectionManagers": {},
							"packageConnectionManagers": {}
						}
					}
				],
				"policy": {
					"elapsedTimeMetric": {},
					"cancelAfter": {}
				},
				"annotations": [],
				"lastPublishTime": "2022-04-20T10:35:38Z"
			},
			"dependsOn": []
		},
		{
			"name": "[concat(parameters('factoryName'), '/P5BI_REPAIRQ_TMO_CETL')]",
			"type": "Microsoft.DataFactory/factories/pipelines",
			"apiVersion": "2018-06-01",
			"properties": {
				"activities": [
					{
						"name": "P5BI_REPAIRQ_TMO_CETL",
						"type": "ExecuteSSISPackage",
						"dependsOn": [],
						"policy": {
							"timeout": "7.00:00:00",
							"retry": 0,
							"retryIntervalInSeconds": 30,
							"secureOutput": false,
							"secureInput": false
						},
						"userProperties": [],
						"typeProperties": {
							"packageLocation": {
								"packagePath": "\\\\sadwfitpoc1.file.core.windows.net\\packagedeploymentssis\\sqlserver\\ssis\\development\\BI\\SSIS\\BI_REPAIRQ\\PR_Data_Audit_Close_ETL_RUN_ID.dtsx",
								"type": "File",
								"typeProperties": {
									"accessCredential": {
										"domain": "Azure",
										"userName": "sadwfitpoc1",
										"password": {
											"type": "SecureString",
											"value": "**********"
										}
									},
									"configurationPath": "\\\\sadwfitpoc1.file.core.windows.net\\packagedeploymentssis\\sqlserver\\ssis\\development\\BI\\Configuration\\BI_REPAIRQ\\REPAIRQTMO.dtsConfig"
								}
							},
							"connectVia": {
								"referenceName": "SSISIR-customtest",
								"type": "IntegrationRuntimeReference"
							},
							"loggingLevel": "Basic",
							"projectConnectionManagers": {},
							"packageConnectionManagers": {},
							"logLocation": {
								"logPath": "\\\\sadwfitpoc1.file.core.windows.net\\packagedeploymentssis\\ASBI\\CONFIGURATION\\BI_REPAIRQ",
								"type": "File",
								"typeProperties": {
									"accessCredential": {
										"domain": "Azure",
										"userName": "sadwfitpoc1",
										"password": {
											"type": "SecureString",
											"value": "**********"
										}
									}
								}
							}
						}
					}
				],
				"policy": {
					"elapsedTimeMetric": {},
					"cancelAfter": {}
				},
				"annotations": [],
				"lastPublishTime": "2022-04-26T06:05:17Z"
			},
			"dependsOn": []
		},
		{
			"name": "[concat(parameters('factoryName'), '/P5BI_REPAIRQ_TMO_DEVICE')]",
			"type": "Microsoft.DataFactory/factories/pipelines",
			"apiVersion": "2018-06-01",
			"properties": {
				"activities": [
					{
						"name": "REPAIRQ_TMO_DEVICE",
						"type": "ExecuteSSISPackage",
						"dependsOn": [],
						"policy": {
							"timeout": "7.00:00:00",
							"retry": 0,
							"retryIntervalInSeconds": 30,
							"secureOutput": false,
							"secureInput": false
						},
						"userProperties": [],
						"typeProperties": {
							"packageLocation": {
								"packagePath": "\\\\sadwfitpoc1.file.core.windows.net\\packagedeploymentssis\\sqlserver\\ssis\\development\\BI\\SSIS\\BI_REPAIRQ\\REPAIRQ_TMO_DEVICE.dtsx",
								"type": "File",
								"typeProperties": {
									"accessCredential": {
										"domain": "Azure",
										"userName": "sadwfitpoc1",
										"password": {
											"type": "SecureString",
											"value": "**********"
										}
									},
									"configurationPath": "\\\\sadwfitpoc1.file.core.windows.net\\packagedeploymentssis\\sqlserver\\ssis\\development\\BI\\Configuration\\DW_REPAIRQ\\REPAIRQTMO.dtsConfig"
								}
							},
							"connectVia": {
								"referenceName": "SSISIR-customtest",
								"type": "IntegrationRuntimeReference"
							},
							"projectConnectionManagers": {},
							"packageConnectionManagers": {}
						}
					}
				],
				"policy": {
					"elapsedTimeMetric": {},
					"cancelAfter": {}
				},
				"annotations": [],
				"lastPublishTime": "2022-04-25T06:20:57Z"
			},
			"dependsOn": []
		},
		{
			"name": "[concat(parameters('factoryName'), '/P5BI_REPAIRQ_TMO_INVENTORY_ITEM')]",
			"type": "Microsoft.DataFactory/factories/pipelines",
			"apiVersion": "2018-06-01",
			"properties": {
				"activities": [
					{
						"name": "REPAIRQ_TMO_INVENTORY_ITEM",
						"type": "ExecuteSSISPackage",
						"dependsOn": [],
						"policy": {
							"timeout": "7.00:00:00",
							"retry": 0,
							"retryIntervalInSeconds": 30,
							"secureOutput": false,
							"secureInput": false
						},
						"userProperties": [],
						"typeProperties": {
							"packageLocation": {
								"packagePath": "\\\\sadwfitpoc1.file.core.windows.net\\packagedeploymentssis\\sqlserver\\ssis\\development\\BI\\SSIS\\BI_REPAIRQ\\REPAIRQ_TMO_INVENTORY_ITEM.dtsx",
								"type": "File",
								"typeProperties": {
									"accessCredential": {
										"domain": "Azure",
										"userName": "sadwfitpoc1",
										"password": {
											"type": "SecureString",
											"value": "**********"
										}
									},
									"configurationPath": "\\\\sadwfitpoc1.file.core.windows.net\\packagedeploymentssis\\sqlserver\\ssis\\development\\BI\\Configuration\\BI_REPAIRQ\\REPAIRQTMO.dtsConfig"
								}
							},
							"connectVia": {
								"referenceName": "SSISIR-customtest",
								"type": "IntegrationRuntimeReference"
							},
							"projectConnectionManagers": {},
							"packageConnectionManagers": {}
						}
					}
				],
				"policy": {
					"elapsedTimeMetric": {},
					"cancelAfter": {}
				},
				"annotations": [],
				"lastPublishTime": "2022-04-25T06:32:01Z"
			},
			"dependsOn": []
		},
		{
			"name": "[concat(parameters('factoryName'), '/P5BI_REPAIRQ_TMO_ITEM_TYPE')]",
			"type": "Microsoft.DataFactory/factories/pipelines",
			"apiVersion": "2018-06-01",
			"properties": {
				"activities": [
					{
						"name": "REPAIRQ_TMO_ITEM_TYPE",
						"type": "ExecuteSSISPackage",
						"dependsOn": [],
						"policy": {
							"timeout": "7.00:00:00",
							"retry": 0,
							"retryIntervalInSeconds": 30,
							"secureOutput": false,
							"secureInput": false
						},
						"userProperties": [],
						"typeProperties": {
							"packageLocation": {
								"packagePath": "\\\\sadwfitpoc1.file.core.windows.net\\packagedeploymentssis\\sqlserver\\ssis\\development\\BI\\SSIS\\BI_REPAIRQ\\REPAIRQ_TMO_ITEM_TYPE.dtsx",
								"type": "File",
								"typeProperties": {
									"accessCredential": {
										"domain": "Azure",
										"userName": "sadwfitpoc1",
										"password": {
											"type": "SecureString",
											"value": "**********"
										}
									},
									"configurationPath": "\\\\sadwfitpoc1.file.core.windows.net\\packagedeploymentssis\\sqlserver\\ssis\\development\\BI\\Configuration\\BI_REPAIRQ\\REPAIRQTMO.dtsConfig"
								}
							},
							"connectVia": {
								"referenceName": "SSISIR-customtest",
								"type": "IntegrationRuntimeReference"
							},
							"projectConnectionManagers": {},
							"packageConnectionManagers": {}
						}
					}
				],
				"policy": {
					"elapsedTimeMetric": {},
					"cancelAfter": {}
				},
				"annotations": [],
				"lastPublishTime": "2022-04-25T06:28:37Z"
			},
			"dependsOn": []
		},
		{
			"name": "[concat(parameters('factoryName'), '/P5BI_REPAIRQ_TMO_REC')]",
			"type": "Microsoft.DataFactory/factories/pipelines",
			"apiVersion": "2018-06-01",
			"properties": {
				"activities": [
					{
						"name": "P5BI_REPAIRQ_TMO_REC",
						"type": "ExecuteSSISPackage",
						"dependsOn": [],
						"policy": {
							"timeout": "7.00:00:00",
							"retry": 0,
							"retryIntervalInSeconds": 30,
							"secureOutput": false,
							"secureInput": false
						},
						"userProperties": [],
						"typeProperties": {
							"packageLocation": {
								"packagePath": "\\\\sadwfitpoc1.file.core.windows.net\\packagedeploymentssis\\sqlserver\\ssis\\development\\BI\\SSIS\\BI_REPAIRQ\\PR_Data_Audit_Reconcile.dtsx",
								"type": "File",
								"typeProperties": {
									"accessCredential": {
										"domain": "Azure",
										"userName": "sadwfitpoc1",
										"password": {
											"type": "SecureString",
											"value": "**********"
										}
									},
									"configurationPath": "\\\\sadwfitpoc1.file.core.windows.net\\packagedeploymentssis\\sqlserver\\ssis\\development\\BI\\Configuration\\BI_REPAIRQ\\REPAIRQTMO.dtsConfig"
								}
							},
							"connectVia": {
								"referenceName": "SSISIR-customtest",
								"type": "IntegrationRuntimeReference"
							},
							"loggingLevel": "Basic",
							"projectConnectionManagers": {},
							"packageConnectionManagers": {},
							"logLocation": {
								"logPath": "\\\\sadwfitpoc1.file.core.windows.net\\packagedeploymentssis\\ASBI\\CONFIGURATION\\BI_REPAIRQ",
								"type": "File",
								"typeProperties": {
									"accessCredential": {
										"domain": "Azure",
										"userName": "sadwfitpoc1",
										"password": {
											"type": "SecureString",
											"value": "**********"
										}
									}
								}
							}
						}
					}
				],
				"policy": {
					"elapsedTimeMetric": {},
					"cancelAfter": {}
				},
				"annotations": [],
				"lastPublishTime": "2022-04-26T06:10:53Z"
			},
			"dependsOn": []
		},
		{
			"name": "[concat(parameters('factoryName'), '/P5BI_REPAIRQ_TMO_SRC')]",
			"type": "Microsoft.DataFactory/factories/pipelines",
			"apiVersion": "2018-06-01",
			"properties": {
				"activities": [
					{
						"name": "P5BI_REPAIRQ_TMO_SRC",
						"type": "ExecuteSSISPackage",
						"dependsOn": [],
						"policy": {
							"timeout": "7.00:00:00",
							"retry": 0,
							"retryIntervalInSeconds": 30,
							"secureOutput": false,
							"secureInput": false
						},
						"userProperties": [],
						"typeProperties": {
							"packageLocation": {
								"packagePath": "\\\\sadwfitpoc1.file.core.windows.net\\packagedeploymentssis\\sqlserver\\ssis\\development\\BI\\SSIS\\BI_REPAIRQ\\PR_Data_Audit_Direct_Source_Table_Count.dtsx",
								"type": "File",
								"typeProperties": {
									"accessCredential": {
										"domain": "Azure",
										"userName": "sadwfitpoc1",
										"password": {
											"type": "SecureString",
											"value": "**********"
										}
									},
									"configurationPath": "\\\\sadwfitpoc1.file.core.windows.net\\packagedeploymentssis\\sqlserver\\ssis\\development\\BI\\Configuration\\BI_REPAIRQ\\REPAIRQTMO.dtsConfig"
								}
							},
							"connectVia": {
								"referenceName": "SSISIR-customtest",
								"type": "IntegrationRuntimeReference"
							},
							"projectConnectionManagers": {},
							"packageConnectionManagers": {}
						}
					}
				],
				"policy": {
					"elapsedTimeMetric": {},
					"cancelAfter": {}
				},
				"annotations": [],
				"lastPublishTime": "2022-04-26T06:07:22Z"
			},
			"dependsOn": []
		},
		{
			"name": "[concat(parameters('factoryName'), '/P5BI_REPAIRQ_TMO_STG')]",
			"type": "Microsoft.DataFactory/factories/pipelines",
			"apiVersion": "2018-06-01",
			"properties": {
				"activities": [
					{
						"name": "P5BI_REPAIRQ_TMO_STG",
						"type": "ExecuteSSISPackage",
						"dependsOn": [],
						"policy": {
							"timeout": "7.00:00:00",
							"retry": 0,
							"retryIntervalInSeconds": 30,
							"secureOutput": false,
							"secureInput": false
						},
						"userProperties": [],
						"typeProperties": {
							"packageLocation": {
								"packagePath": "\\\\sadwfitpoc1.file.core.windows.net\\packagedeploymentssis\\sqlserver\\ssis\\development\\BI\\SSIS\\BI_REPAIRQ\\PR_Data_Audit_Direct_Source_Table_Count.dtsx",
								"type": "File",
								"typeProperties": {
									"accessCredential": {
										"domain": "Azure",
										"userName": "sadwfitpoc1",
										"password": {
											"type": "SecureString",
											"value": "**********"
										}
									},
									"configurationPath": "\\\\sadwfitpoc1.file.core.windows.net\\packagedeploymentssis\\sqlserver\\ssis\\development\\BI\\Configuration\\BI_REPAIRQ\\REPAIRQTMO.dtsConfig"
								}
							},
							"connectVia": {
								"referenceName": "SSISIR-customtest",
								"type": "IntegrationRuntimeReference"
							},
							"loggingLevel": "Basic",
							"projectConnectionManagers": {},
							"packageConnectionManagers": {},
							"logLocation": {
								"logPath": "\\\\sadwfitpoc1.file.core.windows.net\\packagedeploymentssis\\ASBI\\CONFIGURATION\\BI_REPAIRQ",
								"type": "File",
								"typeProperties": {
									"accessCredential": {
										"domain": "Azure",
										"userName": "sadwfitpoc1",
										"password": {
											"type": "SecureString",
											"value": "**********"
										}
									}
								}
							}
						}
					}
				],
				"policy": {
					"elapsedTimeMetric": {},
					"cancelAfter": {}
				},
				"annotations": [],
				"lastPublishTime": "2022-04-26T06:09:13Z"
			},
			"dependsOn": []
		},
		{
			"name": "[concat(parameters('factoryName'), '/P5BI_REPCALENDAR')]",
			"type": "Microsoft.DataFactory/factories/pipelines",
			"apiVersion": "2018-06-01",
			"properties": {
				"activities": [
					{
						"name": "Execute SSIS package1",
						"type": "ExecuteSSISPackage",
						"dependsOn": [],
						"policy": {
							"timeout": "7.00:00:00",
							"retry": 0,
							"retryIntervalInSeconds": 30,
							"secureOutput": false,
							"secureInput": false
						},
						"userProperties": [],
						"typeProperties": {
							"packageLocation": {
								"packagePath": "\\\\sadwfitpoc1.file.core.windows.net\\packagedeploymentssis\\sqlserver\\ssis\\development\\BI\\SSIS\\DW_GW\\PSA_REP_CALENDAR_LOAD.dtsx",
								"type": "File",
								"typeProperties": {
									"accessCredential": {
										"domain": "Azure",
										"userName": "sadwfitpoc1",
										"password": {
											"type": "SecureString",
											"value": "**********"
										}
									},
									"configurationPath": "\\\\sadwfitpoc1.file.core.windows.net\\packagedeploymentssis\\sqlserver\\ssis\\development\\BI\\Configuration\\DW_GW\\PSA_REP_CALENDAR.dtsConfig"
								}
							},
							"connectVia": {
								"referenceName": "SSISIR-customtest",
								"type": "IntegrationRuntimeReference"
							},
							"projectConnectionManagers": {},
							"packageConnectionManagers": {}
						}
					}
				],
				"policy": {
					"elapsedTimeMetric": {},
					"cancelAfter": {}
				},
				"annotations": [],
				"lastPublishTime": "2022-04-25T08:45:45Z"
			},
			"dependsOn": []
		},
		{
			"name": "[concat(parameters('factoryName'), '/P5BI_REPHOLIDAY')]",
			"type": "Microsoft.DataFactory/factories/pipelines",
			"apiVersion": "2018-06-01",
			"properties": {
				"activities": [
					{
						"name": "P5BI_REPHOLIDAY",
						"type": "ExecuteSSISPackage",
						"dependsOn": [],
						"policy": {
							"timeout": "7.00:00:00",
							"retry": 0,
							"retryIntervalInSeconds": 30,
							"secureOutput": false,
							"secureInput": false
						},
						"userProperties": [],
						"typeProperties": {
							"packageLocation": {
								"packagePath": "\\\\sadwfitpoc1.file.core.windows.net\\packagedeploymentssis\\sqlserver\\ssis\\development\\BI\\SSIS\\DW_GW\\PSA_REP_HOLIDAYS_LOAD.dtsx",
								"type": "File",
								"typeProperties": {
									"accessCredential": {
										"domain": "Azure",
										"userName": "sadwfitpoc1",
										"password": {
											"type": "SecureString",
											"value": "**********"
										}
									},
									"configurationPath": "\\\\sadwfitpoc1.file.core.windows.net\\packagedeploymentssis\\sqlserver\\ssis\\development\\BI\\Configuration\\DW_GW\\PSA_REP_HOLIDAYS.dtsConfig"
								}
							},
							"connectVia": {
								"referenceName": "SSISIR-customtest",
								"type": "IntegrationRuntimeReference"
							},
							"projectConnectionManagers": {},
							"packageConnectionManagers": {}
						}
					}
				],
				"policy": {
					"elapsedTimeMetric": {},
					"cancelAfter": {}
				},
				"annotations": [],
				"lastPublishTime": "2022-05-04T12:48:52Z"
			},
			"dependsOn": []
		}
	]
}